odoo/addons/delivery_price_product_domain/README.rst
odoo/addons/delivery_price_product_domain/__init__.py
odoo/addons/delivery_price_product_domain/__manifest__.py
odoo/addons/delivery_price_product_domain/i18n/delivery_price_product_domain.pot
odoo/addons/delivery_price_product_domain/i18n/es.po
odoo/addons/delivery_price_product_domain/i18n/it.po
odoo/addons/delivery_price_product_domain/models/__init__.py
odoo/addons/delivery_price_product_domain/models/delivery_carrier.py
odoo/addons/delivery_price_product_domain/models/delivery_price_rule.py
odoo/addons/delivery_price_product_domain/readme/CONTRIBUTORS.rst
odoo/addons/delivery_price_product_domain/readme/DESCRIPTION.rst
odoo/addons/delivery_price_product_domain/readme/USAGE.rst
odoo/addons/delivery_price_product_domain/static/description/icon.png
odoo/addons/delivery_price_product_domain/static/description/index.html
odoo/addons/delivery_price_product_domain/tests/__init__.py
odoo/addons/delivery_price_product_domain/tests/test_delivery_price_product_domain.py
odoo/addons/delivery_price_product_domain/views/delivery_price_rule_views.xml
odoo14_addon_delivery_price_product_domain-14.0.1.0.4.dist-info/METADATA
odoo14_addon_delivery_price_product_domain-14.0.1.0.4.dist-info/WHEEL
odoo14_addon_delivery_price_product_domain-14.0.1.0.4.dist-info/top_level.txt
odoo14_addon_delivery_price_product_domain-14.0.1.0.4.dist-info/RECORD
