Metadata-Version: 2.1
Name: odoo14-addon-delivery_price_product_domain
Version: 14.0.1.0.4
Summary: Apply domain to product in shipping charges rules
Home-page: https://github.com/OCA/delivery-carrier
Author: Ooops, Cetmix, Odoo Community Association (OCA)
Author-email: support@odoo-community.org
License: AGPL-3
Classifier: Programming Language :: Python
Classifier: Framework :: Odoo
Classifier: Framework :: Odoo :: 14.0
Classifier: License :: OSI Approved :: GNU Affero General Public License v3
Requires-Python: >=3.6
Requires-Dist: odoo14-addon-delivery-price-rule-untaxed
Requires-Dist: odoo<14.1dev,>=14.0a
